lcexoplanet/__init__.py
lcexoplanet/exceptions.py
lcexoplanet/main.py
lcexoplanet/utils.py
lcexoplanet-0.1.2.dist-info/LICENSE
lcexoplanet-0.1.2.dist-info/METADATA
lcexoplanet-0.1.2.dist-info/WHEEL
lcexoplanet-0.1.2.dist-info/top_level.txt
lcexoplanet-0.1.2.dist-info/RECORD
