Metadata-Version: 2.1
Name: lcexoplanet
Version: 0.1.2
Summary: Light Curves for Exoplanets
Home-page: https://github.com/DiegoHS79/lcexoplanet
Author: Diego Hidalgo Soto
Author-email: diego.hidalgo@hotmail.es
Classifier: Programming Language :: Python :: 3
Classifier: License :: OSI Approved :: MIT License
Classifier: Operating System :: OS Independent
License-File: LICENSE
